Metadata-Version: 2.1
Name: nonebot-api-paddleocr
Version: 1.0.3
Summary: nonebot_api_paddleocr
Home-page: https://github.com/canxin121/nonebot_api_paddleocr
Author: canxin
Author-email: 1969730106@qq.com
License: Apache License 2.0
Platform: all
Classifier: Intended Audience :: Developers
Classifier: Operating System :: OS Independent
Classifier: Natural Language :: Chinese (Simplified)
Classifier: Programming Language :: Python
Classifier: Programming Language :: Python :: 3.7
Classifier: Programming Language :: Python :: 3.8
Classifier: Programming Language :: Python :: 3.10
Classifier: Topic :: Software Development :: Libraries
License-File: LICENSE.txt
